blockapi/__init__.py
blockapi/services.py
blockapi/test_data.py
blockapi/test/__init__.py
blockapi/test/test_blockapi.py
blockapi/test/test_num.py
blockapi/test/test_random_user_agent.py
blockapi/test/v2/__init__.py
blockapi/test/v2/test_base.py
blockapi/test/v2/test_blockchain_api.py
blockapi/test/v2/test_blockchain_mapping.py
blockapi/test/v2/test_data.py
blockapi/test/v2/test_enumerate_classes.py
blockapi/test/v2/test_generic.py
blockapi/test/v2/test_models.py
blockapi/test/v2/api/__init__.py
blockapi/test/v2/api/conftest.py
blockapi/test/v2/api/fake_sleep_provider.py
blockapi/test/v2/api/test_blockchainos.py
blockapi/test/v2/api/test_blockchair_btc.py
blockapi/test/v2/api/test_blockchair_doge.py
blockapi/test/v2/api/test_blockchair_ltc.py
blockapi/test/v2/api/test_cosmos.py
blockapi/test/v2/api/test_ethplorer.py
blockapi/test/v2/api/test_multisources.py
blockapi/test/v2/api/test_optimistic_etherscan.py
blockapi/test/v2/api/test_solana.py
blockapi/test/v2/api/test_subscan_polkadot.py
blockapi/test/v2/api/test_sui.py
blockapi/test/v2/api/test_trezor_btc.py
blockapi/test/v2/api/covalenth/__init__.py
blockapi/test/v2/api/covalenth/test_ethereum.py
blockapi/test/v2/api/nft/__init__.py
blockapi/test/v2/api/nft/test_magic_eden.py
blockapi/test/v2/api/nft/test_opensea.py
blockapi/test/v2/api/nft/test_simple_hash.py
blockapi/test/v2/api/nft/test_unisat.py
blockapi/test/v2/api/perpetual/__init__.py
blockapi/test/v2/api/perpetual/test_perpetual.py
blockapi/test/v2/api/synthetix/__init__.py
blockapi/test/v2/api/synthetix/test_synthetix.py
blockapi/utils/__init__.py
blockapi/utils/address.py
blockapi/utils/datetime.py
blockapi/utils/num.py
blockapi/utils/user_agent.py
blockapi/v2/__init__.py
blockapi/v2/base.py
blockapi/v2/blockchain_mapping.py
blockapi/v2/coin_mapping.py
blockapi/v2/coins.py
blockapi/v2/models.py
blockapi/v2/api/__init__.py
blockapi/v2/api/blockchainos.py
blockapi/v2/api/blockchair.py
blockapi/v2/api/cosmos.py
blockapi/v2/api/debank.py
blockapi-2.0.0.dist-info/licenses/LICENSE.md
blockapi-2.0.0.dist-info/METADATA
blockapi-2.0.0.dist-info/WHEEL
blockapi-2.0.0.dist-info/top_level.txt
blockapi-2.0.0.dist-info/RECORD
