Metadata-Version: 2.4
Name: blockapi
Version: 2.0.0
Summary: BlockAPI library
Home-page: https://github.com/crypkit/blockapi
Author: Devmons s.r.o.
License: MIT
License-File: LICENSE.md
Requires-Dist: requests<3.0,>=2.28
Requires-Dist: python-dateutil>=2.8.0
Requires-Dist: coinaddrng==1.1.1
Requires-Dist: web3<8.0.0,>=5.2.2
Requires-Dist: bs4>=0.0.1
Requires-Dist: lxml>=4.4.1
Requires-Dist: pydantic>=1.10.2
Requires-Dist: marko<2.0.0,>=1.3.0
Requires-Dist: fake_useragent>=1.1.3
Requires-Dist: pytest
Requires-Dist: pytest-vcr
Requires-Dist: requests_mock>=1.9.3
Requires-Dist: attrs<23.0.0,>=17.4.0
Requires-Dist: solders>=0.22.0
Dynamic: author
Dynamic: description
Dynamic: description-content-type
Dynamic: home-page
Dynamic: license
Dynamic: license-file
Dynamic: requires-dist
Dynamic: summary
